agility/__init__.py
agility/_base_client.py
agility/_client.py
agility/_compat.py
agility/_constants.py
agility/_exceptions.py
agility/_files.py
agility/_models.py
agility/_qs.py
agility/_resource.py
agility/_response.py
agility/_streaming.py
agility/_types.py
agility/_version.py
agility/pagination.py
agility/py.typed
agility/_utils/__init__.py
agility/_utils/_logs.py
agility/_utils/_proxy.py
agility/_utils/_reflection.py
agility/_utils/_resources_proxy.py
agility/_utils/_streams.py
agility/_utils/_sync.py
agility/_utils/_transform.py
agility/_utils/_typing.py
agility/_utils/_utils.py
agility/lib/.keep
agility/resources/__init__.py
agility/resources/assistants/__init__.py
agility/resources/assistants/access_keys.py
agility/resources/assistants/assistants.py
agility/resources/integrations/__init__.py
agility/resources/integrations/available.py
agility/resources/integrations/integrations.py
agility/resources/integrations/rbac.py
agility/resources/knowledge_bases/__init__.py
agility/resources/knowledge_bases/knowledge_bases.py
agility/resources/knowledge_bases/sources/__init__.py
agility/resources/knowledge_bases/sources/documents.py
agility/resources/knowledge_bases/sources/sources.py
agility/resources/threads/__init__.py
agility/resources/threads/messages.py
agility/resources/threads/runs.py
agility/resources/threads/threads.py
agility/resources/users/__init__.py
agility/resources/users/api_key.py
agility/resources/users/users.py
agility/types/__init__.py
agility/types/assistant.py
agility/types/assistant_create_params.py
agility/types/assistant_list_params.py
agility/types/assistant_list_response.py
agility/types/assistant_retrieve_run_metadata_response.py
agility/types/assistant_update_params.py
agility/types/assistant_with_config.py
agility/types/gc_sv0_integration.py
agility/types/integration.py
agility/types/integration_create_params.py
agility/types/integration_create_response.py
agility/types/integration_list_params.py
agility_sdk-0.0.1.dist-info/METADATA
agility_sdk-0.0.1.dist-info/WHEEL
agility_sdk-0.0.1.dist-info/licenses/LICENSE
agility_sdk-0.0.1.dist-info/RECORD
